RTL/Method1/pointer.v
module synchronous_fifo_pointer #(parameter DEPTH=8, DATA_WIDTH=8) (
input clk, rst_n,
input w_en, r_en,
input [DATA_WIDTH-1:0] data_in,
output reg [DATA_WIDTH-1:0] data_out,
output full, empty);
reg [$clog2(DEPTH)-1:0] w_ptr, r_ptr;
reg [DATA_WIDTH-1:0] fifo[DEPTH-1:0];
// Set Default values on reset.
always@(posedge clk) begin
if(!rst_n) begin
w_ptr <= 0; r_ptr <= 0;
data_out <= 0;
end
end
// To write data to FIFO
always@(posedge clk) begin
if(w_en & !full)begin
fifo[w_ptr] <= data_in;
w_ptr <= w_ptr + 1;
end
end
// To read data from FIFO
always@(posedge clk) begin
if(r_en & !empty) begin
data_out <= fifo[r_ptr];
r_ptr <= r_ptr + 1;
end
end
assign full = ((w_ptr+1'b1) == r_ptr);
assign empty = (w_ptr == r_ptr);
endmodule

src/Method1/tb_pointer.v
`timescale 1ns/1ps
module tb_synchronous_fifo;
// Parameters
parameter DEPTH = 8;
parameter DATA_WIDTH = 8;
// Signals
reg clk, rst_n, w_en, r_en;
reg [DATA_WIDTH-1:0] data_in;
wire [DATA_WIDTH-1:0] data_out;
wire full, empty;
// DUT instantiation
synchronous_fifo_pointer #(DEPTH,
DATA_WIDTH) dut (
.clk(clk),
.rst_n(rst_n),
.w_en(w_en),
.r_en(r_en),
.data_in(data_in),
.data_out(data_out),
.full(full),
.empty(empty) );
// Clock generation
always #5 clk = ~clk;
initial begin
// Initial conditions
clk = 0;
rst_n = 0;
w_en = 0;
r_en = 0;
data_in = 0;
// Reset the DUT
#10;
rst_n = 1;

// Test Case 1: Write to FIFO until full
$display("Test Case 1: Write to FIFO until full");
repeat (DEPTH) begin
#10;
w_en = 1;
data_in = $random % 256; // Random data
end
#10; w_en = 0;
// Check full condition
if (full) $display("FIFO is full as expected");
else $display("FIFO full condition failed");

// Test Case 2: Read from FIFO until empty
$display("Test Case 2: Read from FIFO until empty");
repeat (DEPTH) begin
#10;
r_en = 1;
end
#10;
r_en = 0;
// Check empty condition
if (empty) $display("FIFO is empty as expected");
else $display("FIFO empty condition failed");

// Test Case 3: Parallel Write and Read
$display("Test Case 3: Parallel Write and Read");
repeat (DEPTH / 2) begin
#10;
w_en = 1;
r_en = 1;
data_in = $random % 256; // Random data
end
#10;
w_en = 0;
r_en = 0;

// Test Case 4: Write to Full FIFO
$display("Test Case 4: Write to Full FIFO");
repeat (DEPTH) begin
#10;
w_en = 1;
data_in = $random % 256; // Random data
end
#10;
w_en = 0;
// Attempt to write to full FIFO
#10;
w_en = 1;
data_in = $random % 256; // Random data
#10;
w_en = 0;
if (full) $display("FIFO is full, write operation prevented");
else $display("FIFO full condition failed during write attempt");

//Test Case 5: Read from Empty FIFO
$display("Test Case 5: Read from Empty FIFO");
repeat (DEPTH) begin
#10;
r_en = 1;
end
#10;
r_en = 0;
// Attempt to read from empty FIFO
#10;
r_en = 1;
#10;
r_en = 0;
if (empty) $display("FIFO is empty, read operation prevented");
else $display("FIFO empty condition failed during read attempt");
$stop;
end


initial begin
    $dumpfile("wave.vcd");
    $dumpvars(0, tb_synchronous_fifo);
end 
endmodule

src/Method1/wave.vcd
$date
	Sun Feb 15 22:58:10 2026
$end
$version
	Icarus Verilog
$end
$timescale
	1ps
$end
$scope module tb_synchronous_fifo $end
$var wire 1 ! full $end
$var wire 1 " empty $end
$var wire 8 # data_out [7:0] $end
$var parameter 32 $ DATA_WIDTH $end
$var parameter 32 % DEPTH $end
$var reg 1 & clk $end
$var reg 8 ' data_in [7:0] $end
$var reg 1 ( r_en $end
$var reg 1 ) rst_n $end
$var reg 1 * w_en $end
$scope module dut $end
$var wire 1 & clk $end
$var wire 8 + data_in [7:0] $end
$var wire 1 ( r_en $end
$var wire 1 ) rst_n $end
$var wire 1 * w_en $end
$var wire 1 ! full $end
$var wire 1 " empty $end
$var parameter 32 , DATA_WIDTH $end
$var parameter 32 - DEPTH $end
$var reg 8 . data_out [7:0] $end
$var reg 3 / r_ptr [2:0] $end
$var reg 3 0 w_ptr [2:0] $end
$upscope $end
$upscope $end
$enddefinitions $end
$comment Show the parameter values. $end
$dumpall
b1000 -
b1000 ,
b1000 %
b1000 $
$end
#0
$dumpvars
bx 0
bx /
bx .
b0 +
0*
0)
0(
b0 '
0&
bx #
x"
x!
$end
#5000
b0 #
b0 .
0!
1"
b0 /
b0 0
1&
#10000
0&
1)
#15000
1&
#20000
0&
b100100 '
b100100 +
1*
#25000
0"
b1 0
1&
#30000
0&
b10000001 '
b10000001 +
#35000
b10 0
1&
#40000
0&
b1001 '
b1001 +
#45000
b11 0
1&
#50000
0&
b1100011 '
b1100011 +
#55000
b100 0
1&
#60000
0&
b1101 '
b1101 +
#65000
b101 0
1&
#70000
0&
b10001101 '
b10001101 +
#75000
b110 0
1&
#80000
0&
b1100101 '
b1100101 +
#85000
1!
b111 0
1&
#90000
0&
b10010 '
b10010 +
#95000
1&
#100000
0&
0*
#105000
1&
#110000
0&
1(
#115000
0!
b1 /
b100100 #
b100100 .
1&
#120000
0&
#125000
b10 /
b10000001 #
b10000001 .
1&
#130000
0&
#135000
b11 /
b1001 #
b1001 .
1&
#140000
0&
#145000
b100 /
b1100011 #
b1100011 .
1&
#150000
0&
#155000
b101 /
b1101 #
b1101 .
1&
#160000
0&
#165000
b110 /
b10001101 #
b10001101 .
1&
#170000
0&
#175000
1"
b111 /
b1100101 #
b1100101 .
1&
#180000
0&
#185000
1&
#190000
0&
0(
#195000
1&
#200000
0&
b1 '
b1 +
1(
1*
#205000
0"
b0 0
1&
#210000
0&
b1101 '
b1101 +
#215000
b0 /
b1 #
b1 .
b1 0
1&
#220000
0&
b1110110 '
b1110110 +
#225000
b10 0
0"
b1 /
b1101 #
b1101 .
1&
#230000
0&
b111101 '
b111101 +
#235000
b10 /
b1110110 #
b1110110 .
b11 0
1&
#240000
0&
0(
0*
#245000
1&
#250000
0&
b11101101 '
b11101101 +
1*
#255000
b100 0
1&
#260000
0&
b10001100 '
b10001100 +
#265000
b101 0
1&
#270000
0&
b11111001 '
b11111001 +
#275000
b110 0
1&
#280000
0&
b11000110 '
b11000110 +
#285000
b111 0
1&
#290000
0&
b11000101 '
b11000101 +
#295000
b0 0
1&
#300000
0&
b10101010 '
b10101010 +
#305000
1!
b1 0
1&
#310000
0&
b11100101 '
b11100101 +
#315000
1&
#320000
0&
b1110111 '
b1110111 +
#325000
1&
#330000
0&
0*
#335000
1&
#340000
0&
b10010 '
b10010 +
1*
#345000
1&
#350000
0&
0*
#355000
1&
#360000
0&
1(
#365000
0!
b11 /
b111101 #
b111101 .
1&
#370000
0&
#375000
b100 /
b11101101 #
b11101101 .
1&
#380000
0&
#385000
b101 /
b10001100 #
b10001100 .
1&
#390000
0&
#395000
b110 /
b11111001 #
b11111001 .
1&
#400000
0&
#405000
b111 /
b11000110 #
b11000110 .
1&
#410000
0&
#415000
b0 /
b11000101 #
b11000101 .
1&
#420000
0&
#425000
1"
b1 /
b10101010 #
b10101010 .
1&
#430000
0&
#435000
1&
#440000
0&
0(
#445000
1&
#450000
0&
1(
